[{"__symbolic":"module","version":3,"metadata":{"FragmentComponent":{"__symbolic":"class","extends":{"__symbolic":"reference","module":"../abstract/abstract.component","name":"AbstractComponent"},"decorators":[{"__symbolic":"call","expression":{"__symbolic":"reference","module":"@angular/core","name":"Component"},"arguments":[{"templateUrl":"./fragment.component.html","selector":"kio-fragment","styleUrls":["./fragment.component.scss"]}]}],"members":{"node":[{"__symbolic":"property","decorators":[{"__symbolic":"call","expression":{"__symbolic":"reference","module":"@angular/core","name":"Input"}}]}],"ngOnInit":[{"__symbolic":"method"}],"ngOnDestroy":[{"__symbolic":"method"}]}}}},{"__symbolic":"module","version":1,"metadata":{"FragmentComponent":{"__symbolic":"class","extends":{"__symbolic":"reference","module":"../abstract/abstract.component","name":"AbstractComponent"},"decorators":[{"__symbolic":"call","expression":{"__symbolic":"reference","module":"@angular/core","name":"Component"},"arguments":[{"templateUrl":"./fragment.component.html","selector":"kio-fragment","styleUrls":["./fragment.component.scss"]}]}],"members":{"node":[{"__symbolic":"property","decorators":[{"__symbolic":"call","expression":{"__symbolic":"reference","module":"@angular/core","name":"Input"}}]}],"ngOnInit":[{"__symbolic":"method"}],"ngOnDestroy":[{"__symbolic":"method"}]}}}}]